README.md
setup.py
pituo/__init__.py
pituo/pituo.py
pituo.egg-info/PKG-INFO
pituo.egg-info/SOURCES.txt
pituo.egg-info/dependency_links.txt
pituo.egg-info/top_level.txt