Metadata-Version: 2.1
Name: pituo
Version: 0.0.2
Summary: Go-styled errors in Python.
Home-page: https://github.com/RuyiLi/pituo
Author: Ruyi Li
Author-email: ruyili2002@gmail.com
License: MIT
Keywords: go,error,exception
Platform: UNKNOWN
Classifier: Intended Audience :: Developers
Classifier: License :: OSI Approved :: MIT License
Classifier: Programming Language :: Python :: 3
Classifier: Programming Language :: Python :: 2
Classifier: Operating System :: OS Independent
